{
  "experiment_id": "EXP-MM-1038-ENERGY-STABILITY",
  "problem_id": "Erdos-1038",
  "date": "2026-04-10T17:08:30.307650",
  "config": {
    "N_cloud": 120,
    "atom_pos": 1.0,
    "atom_weight": 0.826,
    "cloud_range": [
      -1.0,
      -0.8
    ],
    "reduced_M": 20,
    "stride": 6
  },
  "experiment_1_energy_mapping": {
    "extremal_log_energy": -0.052071928022843036,
    "extremal_coulomb_energy": 0.5261497491386885,
    "energy_minimizer_atom_weight": 0.808816391052958,
    "energy_minimizer_cloud_support": [
      -0.9999996246792517,
      -0.41713283350883656
    ],
    "energy_minimizer_cloud_CoM": -0.8166318683012962,
    "energy_minimizer_log_energy": -0.05659287902355689,
    "optimizer_converged": true,
    "optimizer_iterations": 18084,
    "riesz_spectrum": {
      "s=0.25": 0.15234339636666638,
      "s=0.5": 0.17148557866567368,
      "s=0.75": 0.25406776704011425,
      "s=1.0": 0.5261497491386885,
      "s=1.5": 4.704026518940442,
      "s=2.0": 70.45976058452779,
      "s=3.0": 31057.56583287144
    },
    "saff_totik_eq_point": -0.5613226452905811,
    "cloud_center_of_mass": -0.9041679762316539
  },
  "experiment_2_stability": {
    "baseline_sublevel": 1.9151999999999998,
    "optimal_atom_weight": 0.85,
    "optimal_cloud_width": 0.3,
    "optimal_cloud_center": -0.95,
    "basin_2d_minimum": {
      "w_atom": 0.85,
      "delta": 0.15000000000000002,
      "sublevel": 1.8537
    },
    "curvature": {
      "d2S_dw2": 245.75999999999914,
      "d2S_dd2": 7.080000000000018,
      "d2S_dwdd": 3.77999999999998,
      "determinant": 1725.6923999999983,
      "trace": 252.83999999999915,
      "classification": "stable_minimum"
    },
    "weight_sensitivity": [
      [
        0.5,
        2.7666
      ],
      [
        0.525,
        2.7662999999999998
      ],
      [
        0.55,
        2.7666
      ],
      [
        0.575,
        2.7659999999999996
      ],
      [
        0.6,
        2.7653999999999996
      ],
      [
        0.625,
        2.7645
      ],
      [
        0.65,
        2.7636
      ],
      [
        0.675,
        2.4981
      ],
      [
        0.7,
        2.34
      ],
      [
        0.725,
        2.2283999999999997
      ],
      [
        0.75,
        2.1437999999999997
      ],
      [
        0.7749999999999999,
        2.0816999999999997
      ],
      [
        0.8,
        2.0442
      ],
      [
        0.825,
        1.9242
      ],
      [
        0.85,
        1.8599999999999999
      ],
      [
        0.875,
        1.8824999999999998
      ],
      [
        0.8999999999999999,
        1.9052999999999998
      ],
      [
        0.925,
        1.9284
      ],
      [
        0.95,
        1.9520999999999997
      ]
    ],
    "delta_sensitivity": [
      [
        0.05,
        1.9010999999999998
      ],
      [
        0.1,
        1.9370999999999998
      ],
      [
        0.15000000000000002,
        1.9775999999999998
      ],
      [
        0.2,
        1.9221
      ],
      [
        0.25,
        1.8950999999999998
      ],
      [
        0.3,
        1.8890999999999998
      ],
      [
        0.35000000000000003,
        1.8974999999999997
      ],
      [
        0.4,
        1.9157999999999997
      ],
      [
        0.45,
        1.9425
      ],
      [
        0.5,
        1.9788
      ],
      [
        0.55,
        2.0309999999999997
      ],
      [
        0.6000000000000001,
        2.0925
      ],
      [
        0.6500000000000001,
        2.2449
      ],
      [
        0.7000000000000001,
        2.2662
      ],
      [
        0.7500000000000001,
        2.2626
      ],
      [
        0.8,
        2.2329
      ]
    ],
    "center_sensitivity": [
      [
        -0.95,
        1.9221
      ],
      [
        -0.8999999999999999,
        1.9221
      ],
      [
        -0.85,
        1.9991999999999999
      ],
      [
        -0.7999999999999999,
        2.0757
      ],
      [
        -0.75,
        2.139
      ],
      [
        -0.7,
        2.1929999999999996
      ],
      [
        -0.6499999999999999,
        2.2742999999999998
      ],
      [
        -0.6,
        2.4612
      ],
      [
        -0.55,
        2.4993
      ],
      [
        -0.5,
        2.4612
      ],
      [
        -0.45,
        2.4246
      ],
      [
        -0.4,
        2.3895
      ],
      [
        -0.35,
        2.3564999999999996
      ],
      [
        -0.30000000000000004,
        2.3253
      ],
      [
        -0.25,
        2.2956
      ],
      [
        -0.20000000000000007,
        2.2676999999999996
      ],
      [
        -0.15000000000000002,
        2.2419
      ],
      [
        -0.09999999999999998,
        2.2176
      ],
      [
        -0.050000000000000044,
        2.1950999999999996
      ],
      [
        0.0,
        2.1740999999999997
      ]
    ],
    "basin_2d_grid": {
      "w_values": [
        0.65,
        0.675,
        0.7,
        0.725,
        0.75,
        0.775,
        0.8,
        0.825,
        0.85,
        0.875,
        0.8999999999999999,
        0.9249999999999999,
        0.95
      ],
      "d_values": [
        0.05,
        0.1,
        0.15000000000000002,
        0.2,
        0.25,
        0.3,
        0.35000000000000003,
        0.4,
        0.45,
        0.5
      ],
      "sublevel_matrix": [
        [
          2.3301,
          2.4227999999999996,
          2.5688999999999997,
          2.7609,
          2.7474,
          2.7356999999999996,
          2.7245999999999997,
          2.7144,
          2.7053999999999996,
          2.6973
        ],
        [
          2.2346999999999997,
          2.3034,
          2.3918999999999997,
          2.5227,
          2.7474,
          2.7363,
          2.7257999999999996,
          2.7165,
          2.7083999999999997,
          2.7011999999999996
        ],
        [
          2.151,
          2.2047,
          2.2704,
          2.3531999999999997,
          2.4665999999999997,
          2.7375,
          2.7281999999999997,
          2.7201,
          2.7131999999999996,
          2.7074999999999996
        ],
        [
          2.0772,
          2.1216,
          2.1740999999999997,
          2.2373999999999996,
          2.3141999999999996,
          2.4143999999999997,
          2.5757999999999996,
          2.7264,
          2.7215999999999996,
          2.7186
        ],
        [
          2.0147999999999997,
          2.0526,
          2.0972999999999997,
          2.1504,
          2.2125,
          2.2862999999999998,
          2.3775,
          2.5025999999999997,
          2.7371999999999996,
          2.7285
        ],
        [
          1.9634999999999998,
          1.9973999999999998,
          2.0378999999999996,
          2.0865,
          2.1429,
          2.2074,
          2.2824,
          2.3192999999999997,
          2.3621999999999996,
          2.4783
        ],
        [
          1.9253999999999998,
          1.9577999999999998,
          1.9986,
          2.0484,
          2.0978999999999997,
          2.0795999999999997,
          2.0747999999999998,
          2.0862,
          2.1218999999999997,
          2.1618
        ],
        [
          1.9013999999999998,
          1.9373999999999998,
          1.9838999999999998,
          1.9304999999999999,
          1.9043999999999999,
          1.8968999999999998,
          1.9028999999999998,
          1.9205999999999999,
          1.9503,
          1.9835999999999998
        ],
        [
          1.8962999999999999,
          1.8636,
          1.8537,
          1.8615,
          1.8699,
          1.8791999999999998,
          1.8890999999999998,
          1.8999,
          1.9119,
          1.9256999999999997
        ],
        [
          1.8657,
          1.8713999999999997,
          1.8770999999999998,
          1.8833999999999997,
          1.8897,
          1.8968999999999998,
          1.9043999999999999,
          1.9124999999999999,
          1.9214999999999998,
          1.9313999999999998
        ],
        [
          1.8926999999999998,
          1.8968999999999998,
          1.9013999999999998,
          1.9059,
          1.9109999999999998,
          1.9161,
          1.9214999999999998,
          1.9274999999999998,
          1.9337999999999997,
          1.9406999999999999
        ],
        [
          1.9196999999999997,
          1.9223999999999999,
          1.926,
          1.9289999999999998,
          1.9325999999999999,
          1.9358999999999997,
          1.9397999999999997,
          1.9439999999999997,
          1.9482,
          1.9529999999999998
        ],
        [
          1.9466999999999999,
          1.9485,
          1.9503,
          1.9524,
          1.9545,
          1.9568999999999999,
          1.9592999999999998,
          1.9616999999999998,
          1.9644,
          1.9673999999999998
        ]
      ]
    }
  },
  "findings": [
    "Log-energy minimizer closely matches sublevel minimizer: w=0.8088 vs 0.826",
    "Single basin at w=0.850, \u03b4=0.150, stable",
    "Cloud tracks Saff-Totik effective potential minimum at x=-0.561"
  ]
}